[
    {
        "name": "Pluto - Project Management Tool",
        "description": "Application with features like Kanban board, backlog, overviews notifications support in Slack",
        "type": "web",
        "technologies": ["React", "Redux", "Firebase", ".NET", "Docker", "Heroku"]
    },
    {
        "name": "Radical - No-Sql Database",
        "description": "Application to manage json documents",
        "type": "web",
        "technologies": ["React", "Redux", ".NET"]
    },
    {
        "name": "Covid Web Application",
        "description": "Web application using covid-19 API to display the actual/current status of the pandemic situation",
        "type": "web",
        "technologies": ["React"]
    },
    {
        "name": "Students management application",
        "description": "An application where you can manage students of an university",
        "type": "web",
        "technologies": [".NET WPF"]
    },
    {
        "name": "Take Notes App",
        "description": "Applicaiton to manage your daily tasks",
        "type": "web & mobile",
        "technologies": ["React", "React Native", "Typescript", "Redux"]
    },
    {
        "name": "Weather Web Application",
        "description": "Web applicaiton to check cities weather information",
        "type": "web",
        "technologies": ["React"]
    }
]